logos_cdi/__init__.py
logos_cdi/abstract.py
logos_cdi/application.py
logos_cdi/command.py
logos_cdi/container.py
logos_cdi/context.py
logos_cdi/error.py
logos_cdi/event.py
logos_cdi/reference.py
logos_cdi/registry.py
logos_cdi/resource.py
logos_cdi-1.1.0.dist-info/licenses/LICENSE
logos_cdi-1.1.0.dist-info/METADATA
logos_cdi-1.1.0.dist-info/WHEEL
logos_cdi-1.1.0.dist-info/entry_points.txt
logos_cdi-1.1.0.dist-info/top_level.txt
logos_cdi-1.1.0.dist-info/RECORD
