Metadata-Version: 2.4
Name: logos-cdi
Version: 1.1.0
Summary: The hackable dependency injection framework
Requires-Python: >=3.12
License-File: LICENSE
Dynamic: license-file
